[
  { "name": "Старт", "type": "start" },
  { "name": "Чернігів", "type": "property", "color": "brown", "price": 600 },
  { "name": "Громадська скарбниця", "type": "community" },
  { "name": "Суми", "type": "property", "color": "brown", "price": 600 },
  { "name": "Прибутковий податок", "type": "tax", "amount": 2000 },
  { "name": "Північна залізниця", "type": "railroad", "direction": "north", "price": 2000 },
  { "name": "Краматорськ", "type": "property", "color": "purple", "price": 1000 },
  { "name": "Шанс", "type": "chance" },
  { "name": "Житомир", "type": "property", "color": "purple", "price": 1000 },
  { "name": "Рівне", "type": "property", "color": "purple", "price": 1200 },
  { "name": "В'язниця", "type": "jail" },

  { "name": "Полтава", "type": "property", "color": "pink", "price": 1400 },
  { "name": "Електростанція", "type": "utility", "utilityType": "electric", "price": 1500 },
  { "name": "Сєвєродонецьк", "type": "property", "color": "pink", "price": 1400 },
  { "name": "Мукачево", "type": "property", "color": "pink", "price": 1600 },
  { "name": "Східна залізниця", "type": "railroad", "direction": "east", "price": 2000 },
  { "name": "Маріуполь", "type": "property", "color": "orange", "price": 1800 },
  { "name": "Громадська скарбниця", "type": "community" },
  { "name": "Запоріжжя", "type": "property", "color": "orange", "price": 1800 },
  { "name": "Івано-Франківськ", "type": "property", "color": "orange", "price": 2000 },

  { "name": "Казино", "type": "casino" },
  { "name": "Херсон", "type": "property", "color": "red", "price": 2200 },
  { "name": "Шанс", "type": "chance" },
  { "name": "Миколаїв", "type": "property", "color": "red", "price": 2200 },
  { "name": "Тернопіль", "type": "property", "color": "red", "price": 2400 },
  { "name": "Південна залізниця", "type": "railroad", "direction": "south", "price": 2000 },
  { "name": "Сімферополь", "type": "property", "color": "yellow", "price": 2600 },
  { "name": "Севастополь", "type": "property", "color": "yellow", "price": 2600 },
  { "name": "Водоканал", "type": "utility", "utilityType": "water", "price": 1500 },
  { "name": "Керч", "type": "property", "color": "yellow", "price": 2800 },

  { "name": "Арешт", "type": "gotojail" },
  { "name": "Ужгород", "type": "property", "color": "green", "price": 3000 },
  { "name": "Харків", "type": "property", "color": "green", "price": 3000 },
  { "name": "Громадська скарбниця", "type": "community" },
  { "name": "Одеса", "type": "property", "color": "green", "price": 3200 },
  { "name": "Західна залізниця", "type": "railroad", "direction": "west", "price": 2000 },
  { "name": "Шанс", "type": "chance" },
  { "name": "Львів", "type": "property", "color": "blue", "price": 3500 },
  { "name": "Податок на розкіш", "type": "tax", "amount": 1000 },
  { "name": "Київ", "type": "property", "color": "blue", "price": 4000 }
]
